CONTRIBUTORS.md
LICENSE
MANIFEST.in
NOTICE
README.md
setup.py
TerminalOne.egg-info/PKG-INFO
TerminalOne.egg-info/SOURCES.txt
TerminalOne.egg-info/dependency_links.txt
TerminalOne.egg-info/requires.txt
TerminalOne.egg-info/top_level.txt
terminalone/__init__.py
terminalone/config.py
terminalone/connection.py
terminalone/entity.py
terminalone/errors.py
terminalone/jsonparser.py
terminalone/metadata.py
terminalone/reports.py
terminalone/service.py
terminalone/t1mappings.py
terminalone/t1mappings_noclassdef.py
terminalone/t1types.py
terminalone/xmlparser.py
terminalone/models/__init__.py
terminalone/models/acl.py
terminalone/models/adserver.py
terminalone/models/advertiser.py
terminalone/models/agency.py
terminalone/models/atomiccreative.py
terminalone/models/audiencesegment.py
terminalone/models/budgetflight.py
terminalone/models/campaign.py
terminalone/models/concept.py
terminalone/models/contact.py
terminalone/models/contract.py
terminalone/models/creative.py
terminalone/models/creativeapproval.py
terminalone/models/deal.py
terminalone/models/organization.py
terminalone/models/permission.py
terminalone/models/pixel.py
terminalone/models/pixelbundle.py
terminalone/models/pixelprovider.py
terminalone/models/placementslot.py
terminalone/models/publisher.py
terminalone/models/publishersite.py
terminalone/models/retiredaudiencesegment.py
terminalone/models/retiredstrategyaudiencesegment.py
terminalone/models/rmxstrategy.py
terminalone/models/rmxstrategyroitargetpixel.py
terminalone/models/seat.py
terminalone/models/sitelist.py
terminalone/models/siteplacement.py
terminalone/models/strategy.py
terminalone/models/strategyaudiencesegment.py
terminalone/models/strategyconcept.py
terminalone/models/strategydaypart.py
terminalone/models/strategydeal.py
terminalone/models/strategydomain.py
terminalone/models/strategysupplysource.py
terminalone/models/strategytargetingsegment.py
terminalone/models/supplysource.py
terminalone/models/targetdimension.py
terminalone/models/targetvalue.py
terminalone/models/user.py
terminalone/models/vendor.py
terminalone/models/vendorcontract.py
terminalone/models/vendordomain.py
terminalone/models/vendorpixel.py
