Metadata-Version: 2.1
Name: TerminalOne
Version: 1.9.20
Summary: A package for interacting with MediaMath's TerminalOne API.
Home-page: http://www.mediamath.com
Author: MediaMath
Author-email: developers@mediamath.com
License: Apache 2.0
Platform: any
Classifier: Development Status :: 5 - Production/Stable
Classifier: License :: OSI Approved :: Apache Software License
Classifier: Programming Language :: Python
Classifier: Programming Language :: Python :: 2.7
Classifier: Programming Language :: Python :: 3
Classifier: Programming Language :: Python :: 3.3
Classifier: Programming Language :: Python :: 3.4
Classifier: Intended Audience :: Developers
Classifier: Natural Language :: English
Classifier: Operating System :: OS Independent
License-File: LICENSE
License-File: NOTICE
